CIAlign/CIAlign
CIAlign/CIAlign.py
CIAlign/__init__.py
CIAlign/_version.py
CIAlign/argP.py
CIAlign/consensusSeq.py
CIAlign/cropDiv.py
CIAlign/cropSeq.py
CIAlign/insertions.py
CIAlign/matrices.py
CIAlign/matrices.txt
CIAlign/miniAlignments.py
CIAlign/palettes.py
CIAlign/parsingFunctions.py
CIAlign/ranges.txt
CIAlign/runCIAlign.py
CIAlign/similarityMatrix.py
CIAlign/utilityFunctions.py
CIAlign/similarity_matrices/BLOSUM100
CIAlign/similarity_matrices/BLOSUM30
CIAlign/similarity_matrices/BLOSUM35
CIAlign/similarity_matrices/BLOSUM40
CIAlign/similarity_matrices/BLOSUM45
CIAlign/similarity_matrices/BLOSUM50
CIAlign/similarity_matrices/BLOSUM55
CIAlign/similarity_matrices/BLOSUM60
CIAlign/similarity_matrices/BLOSUM62
CIAlign/similarity_matrices/BLOSUM65
CIAlign/similarity_matrices/BLOSUM70
CIAlign/similarity_matrices/BLOSUM75
CIAlign/similarity_matrices/BLOSUM80
CIAlign/similarity_matrices/BLOSUM85
CIAlign/similarity_matrices/BLOSUM90
CIAlign/similarity_matrices/BLOSUMN
CIAlign/similarity_matrices/DAYHOFF
CIAlign/similarity_matrices/GONNET
CIAlign/similarity_matrices/IDENTITY
CIAlign/similarity_matrices/MATCH
CIAlign/similarity_matrices/NUC.4.2
CIAlign/similarity_matrices/NUC.4.4
CIAlign/similarity_matrices/PAM10
CIAlign/similarity_matrices/PAM100
CIAlign/similarity_matrices/PAM110
CIAlign/similarity_matrices/PAM120
CIAlign/similarity_matrices/PAM130
CIAlign/similarity_matrices/PAM140
CIAlign/similarity_matrices/PAM150
CIAlign/similarity_matrices/PAM160
CIAlign/similarity_matrices/PAM170
CIAlign/similarity_matrices/PAM180
CIAlign/similarity_matrices/PAM190
CIAlign/similarity_matrices/PAM20
CIAlign/similarity_matrices/PAM200
CIAlign/similarity_matrices/PAM210
CIAlign/similarity_matrices/PAM220
CIAlign/similarity_matrices/PAM230
CIAlign/similarity_matrices/PAM240
CIAlign/similarity_matrices/PAM250
CIAlign/similarity_matrices/PAM260
CIAlign/similarity_matrices/PAM270
CIAlign/similarity_matrices/PAM280
CIAlign/similarity_matrices/PAM290
CIAlign/similarity_matrices/PAM30
cialign-1.1.4.dist-info/LICENSE
cialign-1.1.4.dist-info/METADATA
cialign-1.1.4.dist-info/WHEEL
cialign-1.1.4.dist-info/top_level.txt
cialign-1.1.4.dist-info/RECORD
