Metadata-Version: 2.1
Name: cialign
Version: 1.1.4
Summary: Toolkit for cleaning and interpreting multiple sequence alignments
Home-page: https://github.com/KatyBrown/CIAlign
Author: Charlotte Tumescheit, Katy Brown
Author-email: kab84@cam.ac.uk
Classifier: Programming Language :: Python :: 3
Classifier: License :: OSI Approved :: MIT License
Classifier: Operating System :: OS Independent
License-File: LICENSE
Requires-Dist: matplotlib
Requires-Dist: numpy >=1.21.0
Requires-Dist: ConfigArgParse
Requires-Dist: pillow
